[[{"category": "RiPP", "num_seq": 14930.1, "site": "AEO22_AC_220827_F"}, {"category": "NRPS", "num_seq": 5533.47, "site": "AEO22_AC_220827_F"}, {"category": "other", "num_seq": 12040.21, "site": "AEO22_AC_220827_F"}, {"category": "terpene", "num_seq": 9476.06, "site": "AEO22_AC_220827_F"}, {"category": "PKS", "num_seq": 6074.93, "site": "AEO22_AC_220827_F"}], [{"category": "terpene", "num_seq": 10523.65, "site": "AEO22_BO_220829_F"}, {"category": "RiPP", "num_seq": 17497.7, "site": "AEO22_BO_220829_F"}, {"category": "NRPS", "num_seq": 15426.64, "site": "AEO22_BO_220829_F"}, {"category": "other", "num_seq": 10674.58, "site": "AEO22_BO_220829_F"}, {"category": "PKS", "num_seq": 5153.9, "site": "AEO22_BO_220829_F"}], [{"category": "other", "num_seq": 1832.19, "site": "AEO22_BP2_220829_F"}, {"category": "RiPP", "num_seq": 3653.6, "site": "AEO22_BP2_220829_F"}, {"category": "PKS", "num_seq": 867.28, "site": "AEO22_BP2_220829_F"}, {"category": "NRPS", "num_seq": 979.99, "site": "AEO22_BP2_220829_F"}, {"category": "terpene", "num_seq": 1215.71, "site": "AEO22_BP2_220829_F"}], [{"category": "RiPP", "num_seq": 28319.52, "site": "AEO22_BS_220902_F"}, {"category": "other", "num_seq": 11097.3, "site": "AEO22_BS_220902_F"}, {"category": "NRPS", "num_seq": 5162.49, "site": "AEO22_BS_220902_F"}, {"category": "terpene", "num_seq": 7135.36, "site": "AEO22_BS_220902_F"}, {"category": "PKS", "num_seq": 4516.35, "site": "AEO22_BS_220902_F"}], [{"category": "PKS", "num_seq": 35725.51, "site": "AEO22_CF_220902_F"}, {"category": "RiPP", "num_seq": 75757.76, "site": "AEO22_CF_220902_F"}, {"category": "other", "num_seq": 42267.02, "site": "AEO22_CF_220902_F"}, {"category": "NRPS", "num_seq": 22128.13, "site": "AEO22_CF_220902_F"}, {"category": "terpene", "num_seq": 23059.26, "site": "AEO22_CF_220902_F"}], [{"category": "other", "num_seq": 3601.91, "site": "AEO22_GV_220827_F"}, {"category": "terpene", "num_seq": 9043.63, "site": "AEO22_GV_220827_F"}, {"category": "RiPP", "num_seq": 3985.97, "site": "AEO22_GV_220827_F"}, {"category": "PKS", "num_seq": 2386.05, "site": "AEO22_GV_220827_F"}, {"category": "NRPS", "num_seq": 577.19, "site": "AEO22_GV_220827_F"}], [{"category": "RiPP", "num_seq": 58656.16, "site": "AEO22_HO_220830_F"}, {"category": "PKS", "num_seq": 19206.59, "site": "AEO22_HO_220830_F"}, {"category": "other", "num_seq": 82226.18, "site": "AEO22_HO_220830_F"}, {"category": "NRPS", "num_seq": 25481.5, "site": "AEO22_HO_220830_F"}, {"category": "terpene", "num_seq": 30711.12, "site": "AEO22_HO_220830_F"}], [{"category": "terpene", "num_seq": 17708.33, "site": "AEO22_LB_220827_F"}, {"category": "PKS", "num_seq": 19600.91, "site": "AEO22_LB_220827_F"}, {"category": "RiPP", "num_seq": 34775.68, "site": "AEO22_LB_220827_F"}, {"category": "NRPS", "num_seq": 16576.41, "site": "AEO22_LB_220827_F"}, {"category": "other", "num_seq": 13884.2, "site": "AEO22_LB_220827_F"}], [{"category": "RiPP", "num_seq": 128607.13, "site": "AEO22_TC_220902_F"}, {"category": "other", "num_seq": 62884.54, "site": "AEO22_TC_220902_F"}, {"category": "terpene", "num_seq": 47762.32, "site": "AEO22_TC_220902_F"}, {"category": "PKS", "num_seq": 32487.1, "site": "AEO22_TC_220902_F"}, {"category": "NRPS", "num_seq": 42401.21, "site": "AEO22_TC_220902_F"}], [{"category": "PKS", "num_seq": 15549.81, "site": "CHL22_CA_220323_F"}, {"category": "terpene", "num_seq": 18485.93, "site": "CHL22_CA_220323_F"}, {"category": "RiPP", "num_seq": 40032.35, "site": "CHL22_CA_220323_F"}, {"category": "NRPS", "num_seq": 29282.16, "site": "CHL22_CA_220323_F"}, {"category": "other", "num_seq": 5856.2, "site": "CHL22_CA_220323_F"}], [{"category": "terpene", "num_seq": 64024.99, "site": "CHL22_CC_220324_F"}, {"category": "RiPP", "num_seq": 63500.19, "site": "CHL22_CC_220324_F"}, {"category": "PKS", "num_seq": 44537.02, "site": "CHL22_CC_220324_F"}, {"category": "NRPS", "num_seq": 68068.42, "site": "CHL22_CC_220324_F"}, {"category": "other", "num_seq": 28296.69, "site": "CHL22_CC_220324_F"}], [{"category": "terpene", "num_seq": 9325.49, "site": "CHL22_CE_220402_F"}, {"category": "RiPP", "num_seq": 13763.72, "site": "CHL22_CE_220402_F"}, {"category": "PKS", "num_seq": 7622.92, "site": "CHL22_CE_220402_F"}, {"category": "NRPS", "num_seq": 6907.09, "site": "CHL22_CE_220402_F"}, {"category": "other", "num_seq": 2358.6, "site": "CHL22_CE_220402_F"}], [{"category": "PKS", "num_seq": 20892.33, "site": "CHL22_CH_220319_F"}, {"category": "RiPP", "num_seq": 29462.67, "site": "CHL22_CH_220319_F"}, {"category": "other", "num_seq": 16103.44, "site": "CHL22_CH_220319_F"}, {"category": "terpene", "num_seq": 14489.35, "site": "CHL22_CH_220319_F"}, {"category": "NRPS", "num_seq": 10447.45, "site": "CHL22_CH_220319_F"}], [{"category": "NRPS", "num_seq": 12815.95, "site": "CHL22_CN_220327_F"}, {"category": "other", "num_seq": 9811.27, "site": "CHL22_CN_220327_F"}, {"category": "terpene", "num_seq": 19590.36, "site": "CHL22_CN_220327_F"}, {"category": "RiPP", "num_seq": 15502.9, "site": "CHL22_CN_220327_F"}, {"category": "PKS", "num_seq": 12183.01, "site": "CHL22_CN_220327_F"}], [{"category": "RiPP", "num_seq": 22385.16, "site": "CHL22_CP_220402_F"}, {"category": "terpene", "num_seq": 16469.61, "site": "CHL22_CP_220402_F"}, {"category": "other", "num_seq": 7503.3, "site": "CHL22_CP_220402_F"}, {"category": "PKS", "num_seq": 9734.78, "site": "CHL22_CP_220402_F"}, {"category": "NRPS", "num_seq": 8253.06, "site": "CHL22_CP_220402_F"}], [{"category": "terpene", "num_seq": 39773.53, "site": "CHL22_CR_220324_F"}, {"category": "RiPP", "num_seq": 63193.33, "site": "CHL22_CR_220324_F"}, {"category": "NRPS", "num_seq": 31712.24, "site": "CHL22_CR_220324_F"}, {"category": "other", "num_seq": 22573.75, "site": "CHL22_CR_220324_F"}, {"category": "PKS", "num_seq": 22822.49, "site": "CHL22_CR_220324_F"}], [{"category": "other", "num_seq": 91280.6, "site": "CHL22_CU_220402_F"}, {"category": "RiPP", "num_seq": 148214.65, "site": "CHL22_CU_220402_F"}, {"category": "terpene", "num_seq": 61458.89, "site": "CHL22_CU_220402_F"}, {"category": "PKS", "num_seq": 78096.29, "site": "CHL22_CU_220402_F"}, {"category": "NRPS", "num_seq": 70463.5, "site": "CHL22_CU_220402_F"}], [{"category": "RiPP", "num_seq": 81849.58, "site": "CHL22_CZ_220329_F"}, {"category": "NRPS", "num_seq": 36653.43, "site": "CHL22_CZ_220329_F"}, {"category": "PKS", "num_seq": 25596.41, "site": "CHL22_CZ_220329_F"}, {"category": "terpene", "num_seq": 27985.7, "site": "CHL22_CZ_220329_F"}, {"category": "other", "num_seq": 11792.4, "site": "CHL22_CZ_220329_F"}, {"category": "saccharide", "num_seq": 119.02, "site": "CHL22_CZ_220329_F"}], [{"category": "terpene", "num_seq": 44362.57, "site": "CHL22_EQ_220330_F"}, {"category": "NRPS", "num_seq": 76293.56, "site": "CHL22_EQ_220330_F"}, {"category": "RiPP", "num_seq": 87402.62, "site": "CHL22_EQ_220330_F"}, {"category": "PKS", "num_seq": 35840.88, "site": "CHL22_EQ_220330_F"}, {"category": "other", "num_seq": 40587.04, "site": "CHL22_EQ_220330_F"}], [{"category": "terpene", "num_seq": 66712.3, "site": "CHL22_GB_220322_F"}, {"category": "PKS", "num_seq": 46864.98, "site": "CHL22_GB_220322_F"}, {"category": "RiPP", "num_seq": 91613.36, "site": "CHL22_GB_220322_F"}, {"category": "NRPS", "num_seq": 65475.3, "site": "CHL22_GB_220322_F"}, {"category": "other", "num_seq": 28966.61, "site": "CHL22_GB_220322_F"}], [{"category": "terpene", "num_seq": 64208.78, "site": "CHL22_IS_220328_F"}, {"category": "other", "num_seq": 104163.39, "site": "CHL22_IS_220328_F"}, {"category": "NRPS", "num_seq": 121233.7, "site": "CHL22_IS_220328_F"}, {"category": "RiPP", "num_seq": 147545.8, "site": "CHL22_IS_220328_F"}, {"category": "PKS", "num_seq": 47863.57, "site": "CHL22_IS_220328_F"}], [{"category": "RiPP", "num_seq": 29143.04, "site": "CHL22_JR_220403_F"}, {"category": "PKS", "num_seq": 9600.76, "site": "CHL22_JR_220403_F"}, {"category": "NRPS", "num_seq": 15645.7, "site": "CHL22_JR_220403_F"}, {"category": "terpene", "num_seq": 11726.04, "site": "CHL22_JR_220403_F"}, {"category": "other", "num_seq": 5554.63, "site": "CHL22_JR_220403_F"}], [{"category": "RiPP", "num_seq": 26064.8, "site": "CHL22_LA_220331_F"}, {"category": "NRPS", "num_seq": 9938.53, "site": "CHL22_LA_220331_F"}, {"category": "PKS", "num_seq": 10264.02, "site": "CHL22_LA_220331_F"}, {"category": "terpene", "num_seq": 27970.4, "site": "CHL22_LA_220331_F"}, {"category": "other", "num_seq": 19634.48, "site": "CHL22_LA_220331_F"}], [{"category": "PKS", "num_seq": 46885.51, "site": "CHL22_LC_220316_F"}, {"category": "other", "num_seq": 50709.06, "site": "CHL22_LC_220316_F"}, {"category": "NRPS", "num_seq": 81697.97, "site": "CHL22_LC_220316_F"}, {"category": "RiPP", "num_seq": 38222.68, "site": "CHL22_LC_220316_F"}, {"category": "terpene", "num_seq": 24553.49, "site": "CHL22_LC_220316_F"}], [{"category": "RiPP", "num_seq": 30903.22, "site": "CHL22_LN_220321_F"}, {"category": "terpene", "num_seq": 24088.13, "site": "CHL22_LN_220321_F"}, {"category": "NRPS", "num_seq": 14336.57, "site": "CHL22_LN_220321_F"}, {"category": "PKS", "num_seq": 9025.16, "site": "CHL22_LN_220321_F"}, {"category": "other", "num_seq": 9706.54, "site": "CHL22_LN_220321_F"}], [{"category": "terpene", "num_seq": 45083.02, "site": "CHL22_LP_220401_F"}, {"category": "RiPP", "num_seq": 90367.1, "site": "CHL22_LP_220401_F"}, {"category": "NRPS", "num_seq": 71794.58, "site": "CHL22_LP_220401_F"}, {"category": "PKS", "num_seq": 36624.05, "site": "CHL22_LP_220401_F"}, {"category": "other", "num_seq": 32292.04, "site": "CHL22_LP_220401_F"}], [{"category": "RiPP", "num_seq": 46167.74, "site": "CHL22_LR_220331_F"}, {"category": "PKS", "num_seq": 18481.41, "site": "CHL22_LR_220331_F"}, {"category": "NRPS", "num_seq": 15087.22, "site": "CHL22_LR_220331_F"}, {"category": "other", "num_seq": 18930.24, "site": "CHL22_LR_220331_F"}, {"category": "terpene", "num_seq": 29567.41, "site": "CHL22_LR_220331_F"}], [{"category": "PKS", "num_seq": 23922.69, "site": "CHL22_LV_220331_F"}, {"category": "NRPS", "num_seq": 16586.83, "site": "CHL22_LV_220331_F"}, {"category": "RiPP", "num_seq": 33661.77, "site": "CHL22_LV_220331_F"}, {"category": "terpene", "num_seq": 27235.76, "site": "CHL22_LV_220331_F"}, {"category": "other", "num_seq": 16249.35, "site": "CHL22_LV_220331_F"}]]